{
    "@class": "com.kony.gen.viz.model.component.KVizCheckBox",
    "DNDConfig": null,
    "_height_": {
        "type": "ref",
        "value": "preferred"
    },
    "_left_": {
        "type": "string",
        "value": "0%"
    },
    "_margin_": [
        0,
        0,
        0,
        0
    ],
    "_padding_": [
        0,
        0,
        0,
        0
    ],
    "_render_": true,
    "_skin_": "s9573b1e4d5e441e94b82149522fbd4a",
    "_top_": {
        "type": "string",
        "value": "153%"
    },
    "_width_": {
        "type": "string",
        "value": "100%"
    },
    "canUpdateUI": true,
    "containerweight": 100,
    "id": "cbOnScreen",
    "info": null,
    "ipad": {
        "psp": {
            "viewType": 4
        }
    },
    "isvisible": true,
    "itemorientation": "vertical",
    "kuid": "e69f2845d8024da08104597a2b59f0a2",
    "masterdata": [
        [
            "cbg1",
            "Value 1"
        ],
        [
            "cbg2",
            "Value 2"
        ],
        [
            "cbg3",
            "Value 3"
        ]
    ],
    "name": "kony.ui.CheckBoxGroup",
    "orientation": "vertical",
    "parent": "frmChk",
    "pf": "frmChk",
    "selectedkey": null,
    "selectedkeys": [
        "cbg1"
    ],
    "selectedkeyvalue": null,
    "selectedkeyvalues": [
        [
            "cbg1",
            "Value 1"
        ]
    ],
    "size": 18,
    "spabb": {
        "render": false
    },
    "viewtype": 0,
    "wType": "CheckBoxGroup",
    "widgetalignment": 5,
    "zindex": 1
}