{
    "@class": "com.kony.gen.viz.model.container.KVizScrollFlexForm",
    "DNDConfig": null,
    "_margin_": [
        0,
        0,
        0,
        0
    ],
    "_orientation_": 1,
    "_padding_": [
        0,
        0,
        0,
        0
    ],
    "_percent_": true,
    "_pxMenuIndex": [
        0,
        1,
        127
    ],
    "_skin_": "s2569ba4728e4822bb4ea17f7c6bd3ae",
    "_title_": null,
    "addWidgetsdone": false,
    "allboxes": [],
    "breakpointInfo": {
        "b1": {
            "width": 1366
        },
        "b2": {
            "width": 1024
        },
        "b3": {
            "width": 640
        }
    },
    "canUpdateUI": true,
    "children": [
        "labl",
        "lbl1",
        "TextField0b948d870dc044d",
        "Copylbl0c8794b12c6454f",
        "CopyTextField08f9f9364a52449",
        "Copylbl0b78167bd2c7e42",
        "CopyTextField0de477f87aff745",
        "Copylbl0952debef82fb46",
        "CopyTextField0c12530be25234c",
        "CopyTextField0379d59d3dc5342",
        "Copylbl034df119fcea244",
        "Copylbl0a82708abcc4847",
        "CopyTextField01b100602574049",
        "Copylbl010bf60a5744542",
        "CopyTextField07c52f4d00d944a",
        "navHome"
    ],
    "containerweight": 100,
    "currentLocale": "default",
    "desktopweb": {
        "needAppMenu": false
    },
    "displayorientation": 1,
    "enabledforidletimeout": false,
    "id": "frmTbx",
    "info": null,
    "initdone": false,
    "inputaccessoryviewtype": 4,
    "ipad": {
        "psp": {
            "inputAccessoryViewType": 4
        }
    },
    "isvisible": true,
    "kuid": "e0ea96eaf5db4c3aaea2afec177dd88b",
    "layouttype": 2,
    "name": "kony.ui.Form2",
    "needappmenu": true,
    "paddinginpixel": false,
    "retainscrollposition": false,
    "snapgridsize": 10,
    "snaptogrid": true,
    "titleBarSkin": "s01a3c761ed44dcab0d6537d1b55b621",
    "titlebar": true,
    "type": 3,
    "wType": "Form"
}